nameko_query/__init__.py
nameko_query/request.py
nameko_query/responder.py
nameko_query-0.0.2.dist-info/DESCRIPTION.rst
nameko_query-0.0.2.dist-info/METADATA
nameko_query-0.0.2.dist-info/RECORD
nameko_query-0.0.2.dist-info/WHEEL
nameko_query-0.0.2.dist-info/entry_points.txt
nameko_query-0.0.2.dist-info/metadata.json
nameko_query-0.0.2.dist-info/top_level.txt
